anitomy.py-1.0.0.dist-info/METADATA
anitomy.py-1.0.0.dist-info/RECORD
anitomy.py-1.0.0.dist-info/WHEEL
anitomy.py-1.0.0.dist-info/top_level.txt
anitopy/__init__.py
anitopy/anitopy.py
anitopy/element.py
anitopy/keyword.py
anitopy/parser.py
anitopy/parser_helper.py
anitopy/parser_number.py
anitopy/token.py
anitopy/tokenizer.py
